AUTHORS.md
LICENSE
README.md
setup.cfg
setup.py
canvasapi/__init__.py
canvasapi/account.py
canvasapi/account_calendar.py
canvasapi/appointment_group.py
canvasapi/assignment.py
canvasapi/authentication_event.py
canvasapi/authentication_provider.py
canvasapi/avatar.py
canvasapi/blueprint.py
canvasapi/bookmark.py
canvasapi/calendar_event.py
canvasapi/canvas.py
canvasapi/canvas_object.py
canvasapi/collaboration.py
canvasapi/comm_message.py
canvasapi/communication_channel.py
canvasapi/content_export.py
canvasapi/content_migration.py
canvasapi/conversation.py
canvasapi/course.py
canvasapi/course_epub_export.py
canvasapi/course_event.py
canvasapi/current_user.py
canvasapi/custom_gradebook_columns.py
canvasapi/discussion_topic.py
canvasapi/enrollment.py
canvasapi/enrollment_term.py
canvasapi/eportfolio.py
canvasapi/exceptions.py
canvasapi/external_feed.py
canvasapi/external_tool.py
canvasapi/favorite.py
canvasapi/feature.py
canvasapi/file.py
canvasapi/folder.py
canvasapi/grade_change_log.py
canvasapi/gradebook_history.py
canvasapi/grading_period.py
canvasapi/grading_standard.py
canvasapi/group.py
canvasapi/jwt.py
canvasapi/license.py
canvasapi/login.py
canvasapi/module.py
canvasapi/new_quiz.py
canvasapi/notification_preference.py
canvasapi/outcome.py
canvasapi/outcome_import.py
canvasapi/page.py
canvasapi/page_view.py
canvasapi/paginated_list.py
canvasapi/pairing_code.py
canvasapi/peer_review.py
canvasapi/planner.py
canvasapi/poll.py
canvasapi/poll_choice.py
canvasapi/poll_session.py
canvasapi/poll_submission.py
canvasapi/progress.py
canvasapi/quiz.py
canvasapi/quiz_group.py
canvasapi/requester.py
canvasapi/rubric.py
canvasapi/scope.py
canvasapi/section.py
canvasapi/sis_import.py
canvasapi/submission.py
canvasapi/tab.py
canvasapi/todo.py
canvasapi/upload.py
canvasapi/usage_rights.py
canvasapi/user.py
canvasapi/util.py
canvasapi_Belovolov.egg-info/PKG-INFO
canvasapi_Belovolov.egg-info/SOURCES.txt
canvasapi_Belovolov.egg-info/dependency_links.txt
canvasapi_Belovolov.egg-info/not-zip-safe
canvasapi_Belovolov.egg-info/requires.txt
canvasapi_Belovolov.egg-info/top_level.txt