Metadata-Version: 2.1
Name: canvasapi-Belovolov
Version: 3.2.2
Summary: API wrapper for the Canvas LMS with a fix of the original canvasapi package
Home-page: https://github.com/Belovolov/canvasapi
Author: Roman Belovolov
Author-email: belovolovri@gmail.com
License: MIT License
Classifier: Development Status :: 5 - Production/Stable
Classifier: Intended Audience :: Developers
Classifier: Intended Audience :: Education
Classifier: Intended Audience :: Information Technology
Classifier: License :: OSI Approved :: MIT License
Classifier: Operating System :: OS Independent
Classifier: Programming Language :: Python
Classifier: Programming Language :: Python :: 3.7
Classifier: Programming Language :: Python :: 3.8
Classifier: Programming Language :: Python :: 3.9
Classifier: Programming Language :: Python :: 3.10
Classifier: Programming Language :: Python :: 3.11
Classifier: Topic :: Software Development :: Libraries
License-File: LICENSE
License-File: AUTHORS.md
